json_document
