Metadata-Version: 1.1
Name: json-document
Version: 0.8
Summary: Powerful and intuitive document bridge for JSON
Home-page: http://github.com/zyga/json-document/
Author: Zygmunt Krynicki
Author-email: zygmunt.krynicki@linaro.org
License: LGPLv3
Platform: UNKNOWN
Classifier: Development Status :: 3 - Alpha
Classifier: Intended Audience :: Developers
Classifier: License :: OSI Approved :: GNU Library or Lesser General Public License (LGPL)
Classifier: Operating System :: OS Independent
Classifier: Programming Language :: Python :: 2.6
Classifier: Programming Language :: Python :: 2.7
Classifier: Topic :: Software Development :: Build Tools
Classifier: Topic :: Software Development :: Testing
